arq_alight/__init__.py
arq_alight/__main__.py
arq_alight/auth/__init__.py
arq_alight/auth/credentials.py
arq_alight/cli.py
arq_alight/compression/__init__.py
arq_alight/config/__init__.py
arq_alight/config/manager.py
arq_alight/core/__init__.py
arq_alight/core/exceptions.py
arq_alight/core/models.py
arq_alight/crypto/__init__.py
arq_alight/py.typed
arq_alight/storage/__init__.py
arq_alight/storage/readonly_s3.py
arq_alight/utils/__init__.py
arq_alight/utils/security.py
arq_alight-0.0.1.dist-info/WHEEL
arq_alight-0.0.1.dist-info/entry_points.txt
arq_alight-0.0.1.dist-info/METADATA
arq_alight-0.0.1.dist-info/RECORD
