Metadata-Version: 2.3
Name: arq-alight
Version: 0.0.1
Summary: Python library and CLI for restoring Arq backups on macOS
Author: Anthony Wu
Author-email: Anthony Wu <pls-file-gh-issue@users.noreply.github.com>
License: MIT
Classifier: Development Status :: 3 - Alpha
Classifier: Intended Audience :: Developers
Classifier: License :: OSI Approved :: MIT License
Classifier: Operating System :: MacOS :: MacOS X
Classifier: Programming Language :: Python :: 3
Classifier: Programming Language :: Python :: 3.11
Classifier: Programming Language :: Python :: 3.12
Classifier: Programming Language :: Python :: 3.13
Requires-Dist: boto3>=1.40,<2.0
Requires-Dist: cryptography>=45.0,<46.0
Requires-Dist: lz4>=4.4,<5.0
Requires-Dist: rich>=14.1,<15.0
Requires-Dist: pytest>=7.4,<8.0 ; extra == 'dev'
Requires-Dist: pytest-asyncio>=0.21,<1.0 ; extra == 'dev'
Requires-Dist: pytest-mock>=3.12,<4.0 ; extra == 'dev'
Requires-Dist: ruff>=0.8,<1.0 ; extra == 'dev'
Requires-Python: >=3.11
Provides-Extra: dev
